apimatic_coin_gecko_api-1.0.0.dist-info/licenses/LICENSE
coingeckopublicapiv3/__init__.py
coingeckopublicapiv3/api_helper.py
coingeckopublicapiv3/coingeckopublicapiv_3_client.py
coingeckopublicapiv3/configuration.py
coingeckopublicapiv3/controllers/__init__.py
coingeckopublicapiv3/controllers/asset_platforms_controller.py
coingeckopublicapiv3/controllers/base_controller.py
coingeckopublicapiv3/controllers/categories_controller.py
coingeckopublicapiv3/controllers/coins_controller.py
coingeckopublicapiv3/controllers/companies_beta_controller.py
coingeckopublicapiv3/controllers/contract_controller.py
coingeckopublicapiv3/controllers/derivatives_controller.py
coingeckopublicapiv3/controllers/exchange_rates_controller.py
coingeckopublicapiv3/controllers/exchanges_controller.py
coingeckopublicapiv3/controllers/global_controller.py
coingeckopublicapiv3/controllers/nf_ts_beta_controller.py
coingeckopublicapiv3/controllers/ping_controller.py
coingeckopublicapiv3/controllers/search_controller.py
coingeckopublicapiv3/controllers/simple_controller.py
coingeckopublicapiv3/controllers/trending_controller.py
coingeckopublicapiv3/exceptions/__init__.py
coingeckopublicapiv3/exceptions/api_exception.py
coingeckopublicapiv3/http/__init__.py
coingeckopublicapiv3/http/http_call_back.py
coingeckopublicapiv3/http/http_method_enum.py
coingeckopublicapiv3/http/http_request.py
coingeckopublicapiv3/http/http_response.py
coingeckopublicapiv3/http/auth/__init__.py
coingeckopublicapiv3/http/auth/api_key_auth.py
coingeckopublicapiv3/http/auth/api_key_query_param.py
coingeckopublicapiv3/models/__init__.py
coingeckopublicapiv3/models/asset_platform.py
coingeckopublicapiv3/models/ath.py
coingeckopublicapiv3/models/ath_1.py
coingeckopublicapiv3/models/ath_change_percentage.py
coingeckopublicapiv3/models/ath_change_percentage_1.py
coingeckopublicapiv3/models/ath_date.py
coingeckopublicapiv3/models/ath_date_1.py
coingeckopublicapiv3/models/atl.py
coingeckopublicapiv3/models/atl_change_percentage.py
coingeckopublicapiv3/models/atl_date.py
apimatic_coin_gecko_api-1.0.0.dist-info/METADATA
apimatic_coin_gecko_api-1.0.0.dist-info/WHEEL
apimatic_coin_gecko_api-1.0.0.dist-info/top_level.txt
apimatic_coin_gecko_api-1.0.0.dist-info/RECORD
