Metadata-Version: 2.4
Name: apimatic-coin-gecko-api
Version: 1.0.0
Summary: CoinGecko Public API V3 provides comprehensive cryptocurrency market data including real-time prices, market caps, trading volumes, exchange information, and historical charts for thousands of cryptocurrencies across multiple currencies and asset platforms.
Author-email: Muhammad Hamza Shahzad <muhammad.hamza@apimatic.io>
Project-URL: Documentation, https://docs.apimatic.io/
Requires-Python: >=3.7
License-File: LICENSE
Requires-Dist: apimatic-core>=0.2.20,~=0.2.0
Requires-Dist: apimatic-core-interfaces>=0.1.5,~=0.1.0
Requires-Dist: apimatic-requests-client-adapter>=0.1.6,~=0.1.0
Provides-Extra: testutils
Requires-Dist: pytest>=7.2.2; extra == "testutils"
Dynamic: license-file
